sjtuq/__init__.py
sjtuq/utils.py
sjtu_questionnaire-0.1.0.dist-info/LICENSE
sjtu_questionnaire-0.1.0.dist-info/WHEEL
sjtu_questionnaire-0.1.0.dist-info/METADATA
sjtu_questionnaire-0.1.0.dist-info/RECORD
