Metadata-Version: 2.1
Name: sjtu-questionnaire
Version: 0.1.0
Summary: A Python binding to SJTU Questionnaire API (https://wj.sjtu.edu.cn/)
Home-page: https://github.com/Gennadiyev/sjtuq
License: MIT
Author: Kunologist
Author-email: kunologist@foxmail.com
Maintainer: Kunologist
Maintainer-email: kunologist@foxmail.com
Requires-Python: >=3.7,<4.0
Classifier: Development Status :: 4 - Beta
Classifier: Intended Audience :: Developers
Classifier: License :: OSI Approved :: MIT License
Classifier: Operating System :: OS Independent
Classifier: Programming Language :: Python :: 3
Classifier: Programming Language :: Python :: 3.10
Classifier: Programming Language :: Python :: 3.7
Classifier: Programming Language :: Python :: 3.8
Classifier: Programming Language :: Python :: 3.9
Requires-Dist: requests (>=2.6.0,<3.0.0)
Project-URL: Bug Tracker, https://github.com/Gennadiyev/sjtuq/issues
Project-URL: Documentation, https://gennadiyev.github.io/sjtu-questionnaire/index.html
Project-URL: Repository, https://github.com/Gennadiyev/sjtuq
